tpkm/__init__.py
tpkm/kafka_client.py
tpkm/kafka_consumer_manager.py
tpkm/kafka_manager.py
tpkm/kafka_message.py
tpkm/kafka_message_consumer.py
tpkm/kafka_message_handler.py
tpkm/module_globals.py
tpkm/retry_policy.py
tpkm-0.1.0.dist-info/LICENSE
tpkm-0.1.0.dist-info/METADATA
tpkm-0.1.0.dist-info/WHEEL
tpkm-0.1.0.dist-info/RECORD
