Metadata-Version: 2.3
Name: tpkm
Version: 0.1.0
Summary: Typed Python Kafka Manager - easy publish/listen to kafka topics embraced with strong types
License: Apache 2.0
Author: Szymon Dudziak
Author-email: sz.dudziak@gmail.com
Requires-Python: >=3.9
Classifier: License :: Other/Proprietary License
Classifier: Programming Language :: Python :: 3
Classifier: Programming Language :: Python :: 3.9
Classifier: Programming Language :: Python :: 3.10
Classifier: Programming Language :: Python :: 3.11
Classifier: Programming Language :: Python :: 3.12
Classifier: Programming Language :: Python :: 3.13
Requires-Dist: confluent-kafka (>=2.10.0,<3.0.0)
Requires-Dist: dacite (>=1.9.2,<2.0.0)
